src/__init__.py
src/app.py
src/callbacks.py
src/preprocessing.py
src/structurecontainer.py
src/visualization/__init__.py
src/visualization/assets/logo.png
src/visualization/assets/offcanvas.css
src/visualization/assets/toast.css
src/visualization/base.py
src/visualization/pdb.py
src/visualization/visualizator.py
rostspace-0.1.1.dist-info/entry_points.txt
rostspace-0.1.1.dist-info/LICENSE
rostspace-0.1.1.dist-info/WHEEL
rostspace-0.1.1.dist-info/METADATA
rostspace-0.1.1.dist-info/RECORD
