Metadata-Version: 2.1
Name: rostspace
Version: 0.1.1
Summary: Protein Embedding Visualization Tool.
Home-page: https://github.com/Rostlab/RostSpace
License: AGPL-3.0-or-later
Keywords: Embeddings,Protein-Sequences,Visualisation
Author: Anton Spannagl
Maintainer: Rostlab
Maintainer-email: admin@rostlab.org
Requires-Python: >=3.9,<4.0
Classifier: License :: OSI Approved :: GNU Affero General Public License v3 or later (AGPLv3+)
Classifier: Programming Language :: Python :: 3
Classifier: Programming Language :: Python :: 3.9
Classifier: Programming Language :: Python :: 3.10
Classifier: Programming Language :: Python :: 3.11
Requires-Dist: dash (>=2.6.1,<3.0.0)
Requires-Dist: dash-bio (>=1.0.2,<2.0.0)
Requires-Dist: dash-bootstrap-components (>=1.3.0,<2.0.0)
Requires-Dist: h5py (>=3.7.0,<4.0.0)
Requires-Dist: kaleido (==0.2.1)
Requires-Dist: llvmlite (>=0.39.1,<0.40.0)
Requires-Dist: matplotlib (>=3.5.3,<4.0.0)
Requires-Dist: numpy (>=1.23.3,<2.0.0)
Requires-Dist: pandas (>=1.4.4,<2.0.0)
Requires-Dist: plotly (>=5.10.0,<6.0.0)
Requires-Dist: pyfaidx (>=0.7.1,<0.8.0)
Requires-Dist: pyyaml (>=6.0,<7.0)
Requires-Dist: seaborn (>=0.12.0,<0.13.0)
Requires-Dist: umap-learn (>=0.5.3,<0.6.0)
Project-URL: Repository, https://github.com/Rostlab/RostSpace
